slat/__init__.py
slat/errors.py
slat/log_util.py
slat/response.py
slat/types.py
slat-0.3.1.dist-info/LICENSE
slat-0.3.1.dist-info/METADATA
slat-0.3.1.dist-info/WHEEL
slat-0.3.1.dist-info/top_level.txt
slat-0.3.1.dist-info/RECORD
