Metadata-Version: 2.1
Name: slat
Version: 0.3.1
Summary: Simple Lambda Toolkit
Home-page: https://github.com/samkeen/SLaT
Author: Sam Keen
Author-email: sam.sjk@gmail.com
License: UNKNOWN
Platform: UNKNOWN
Classifier: Programming Language :: Python :: 3
Classifier: License :: OSI Approved :: Apache Software License
Classifier: Operating System :: OS Independent
Requires-Dist: structlog
